gnv/__init__.py
gnv/cli.py
gnv/commands/__init__.py
gnv/commands/cmd_git.py
gnv-1.0.8.dist-info/LICENSE.txt
gnv-1.0.8.dist-info/METADATA
gnv-1.0.8.dist-info/WHEEL
gnv-1.0.8.dist-info/entry_points.txt
gnv-1.0.8.dist-info/top_level.txt
gnv-1.0.8.dist-info/RECORD
