Metadata-Version: 2.1
Name: gnv
Version: 1.0.8
Summary: An automation tool to control GitHub, using the developers terminal with cool automation
Home-page: https://pypi.org/project/gnv/
Author: GN Vageesh
Author-email: vageeshgn2005@gmail.com
Maintainer: GN Vageesh
Maintainer-email: vageeshgn2005@gmail.com
License: MIT
Download-URL: https://github.com/GNVageesh/gnv
Keywords: python,python3,automation,console,click,selenium,easy,hacks,cli
Platform: UNKNOWN
Classifier: License :: OSI Approved :: MIT License
Classifier: Intended Audience :: Developers
Classifier: Operating System :: Unix
Classifier: Operating System :: MacOS :: MacOS X
Classifier: Operating System :: Microsoft :: Windows
Classifier: Programming Language :: Python :: 3
Classifier: Environment :: Console
Classifier: Development Status :: 5 - Production/Stable
Requires-Dist: click (>=7.1.2)
Requires-Dist: selenium (>=3.141.0)
